extract_pdf_images/__init__.py
extract_pdf_images/app.py
extract_pdf_images-1.0.1.dist-info/licenses/LICENSE
extract_pdf_images-1.0.1.dist-info/METADATA
extract_pdf_images-1.0.1.dist-info/WHEEL
extract_pdf_images-1.0.1.dist-info/entry_points.txt
extract_pdf_images-1.0.1.dist-info/top_level.txt
extract_pdf_images-1.0.1.dist-info/RECORD
