Metadata-Version: 2.4
Name: extract-pdf-images
Version: 1.0.1
Summary: A lightweight GUI tool to visualize and extract images from PDF files
Author-email: PDF Image Extractor <example@example.com>
License: MIT
Project-URL: Homepage, https://github.com/bpiwowar/pdf-image-extractor
Project-URL: Repository, https://github.com/bpiwowar/pdf-image-extractor
Keywords: pdf,image,extraction,gui,tkinter
Classifier: Development Status :: 4 - Beta
Classifier: Intended Audience :: End Users/Desktop
Classifier: License :: OSI Approved :: MIT License
Classifier: Programming Language :: Python :: 3
Classifier: Programming Language :: Python :: 3.10
Classifier: Programming Language :: Python :: 3.11
Classifier: Programming Language :: Python :: 3.12
Classifier: Programming Language :: Python :: 3.13
Classifier: Programming Language :: Python :: 3.14
Classifier: Topic :: Multimedia :: Graphics
Requires-Python: >=3.10
License-File: LICENSE
Requires-Dist: PyMuPDF>=1.23.0
Requires-Dist: Pillow>=10.0.0
Requires-Dist: PySide6>=6.5.0
Dynamic: license-file
